{"grid":[[{"xPos":0,"yPos":0,"value":0,"isMine":false,"isRevealed":true,"isFlagged":false},{"xPos":0,"yPos":1,"value":0,"isMine":false,"isRevealed":true,"isFlagged":false},{"xPos":0,"yPos":2,"value":0,"isMine":false,"isRevealed":true,"isFlagged":false},{"xPos":0,"yPos":3,"value":1,"isMine":false,"isRevealed":true,"isFlagged":false},{"xPos":0,"yPos":4,"value":"M","isMine":true,"isRevealed":false,"isFlagged":false},{"xPos":0,"yPos":5,"value":1,"isMine":false,"isRevealed":false,"isFlagged":false},{"xPos":0,"yPos":6,"value":1,"isMine":false,"isRevealed":false,"isFlagged":false},{"xPos":0,"yPos":7,"value":"M","isMine":true,"isRevealed":false,"isFlagged":false},{"xPos":0,"yPos":8,"value":1,"isMine":false,"isRevealed":false,"isFlagged":false},{"xPos":0,"yPos":9,"value":0,"isMine":false,"isRevealed":false,"isFlagged":false}],[{"xPos":1,"yPos":0,"value":1,"isMine":false,"isRevealed":true,"isFlagged":false},{"xPos":1,"yPos":1,"value":1,"isMine":false,"isRevealed":true,"isFlagged":false},{"xPos":1,"yPos":2,"value":0,"isMine":false,"isRevealed":true,"isFlagged":false},{"xPos":1,"yPos":3,"value":1,"isMine":false,"isRevealed":true,"isFlagged":false},{"xPos":1,"yPos":4,"value":1,"isMine":false,"isRevealed":true,"isFlagged":false},{"xPos":1,"yPos":5,"value":2,"isMine":false,"isRevealed":true,"isFlagged":false},{"xPos":1,"yPos":6,"value":2,"isMine":false,"isRevealed":false,"isFlagged":false},{"xPos":1,"yPos":7,"value":3,"isMine":false,"isRevealed":false,"isFlagged":false},{"xPos":1,"yPos":8,"value":2,"isMine":false,"isRevealed":false,"isFlagged":false},{"xPos":1,"yPos":9,"value":1,"isMine":false,"isRevealed":false,"isFlagged":false}],[{"xPos":2,"yPos":0,"value":"M","isMine":true,"isRevealed":false,"isFlagged":true},{"xPos":2,"yPos":1,"value":1,"isMine":false,"isRevealed":true,"isFlagged":false},{"xPos":2,"yPos":2,"value":0,"isMine":false,"isRevealed":true,"isFlagged":false},{"xPos":2,"yPos":3,"value":0,"isMine":false,"isRevealed":true,"isFlagged":false},{"xPos":2,"yPos":4,"value":0,"isMine":false,"isRevealed":true,"isFlagged":false},{"xPos":2,"yPos":5,"value":1,"isMine":false,"isRevealed":true,"isFlagged":false},{"xPos":2,"yPos":6,"value":"M","isMine":true,"isRevealed":false,"isFlagged":false},{"xPos":2,"yPos":7,"value":2,"isMine":false,"isRevealed":false,"isFlagged":false},{"xPos":2,"yPos":8,"value":"M","isMine":true,"isRevealed":false,"isFlagged":false},{"xPos":2,"yPos":9,"value":1,"isMine":false,"isRevealed":false,"isFlagged":false}],[{"xPos":3,"yPos":0,"value":1,"isMine":false,"isRevealed":true,"isFlagged":false},{"xPos":3,"yPos":1,"value":2,"isMine":false,"isRevealed":true,"isFlagged":false},{"xPos":3,"yPos":2,"value":1,"isMine":false,"isRevealed":true,"isFlagged":false},{"xPos":3,"yPos":3,"value":1,"isMine":false,"isRevealed":true,"isFlagged":false},{"xPos":3,"yPos":4,"value":0,"isMine":false,"isRevealed":true,"isFlagged":false},{"xPos":3,"yPos":5,"value":1,"isMine":false,"isRevealed":true,"isFlagged":false},{"xPos":3,"yPos":6,"value":1,"isMine":false,"isRevealed":true,"isFlagged":false},{"xPos":3,"yPos":7,"value":2,"isMine":false,"isRevealed":true,"isFlagged":false},{"xPos":3,"yPos":8,"value":1,"isMine":false,"isRevealed":true,"isFlagged":false},{"xPos":3,"yPos":9,"value":1,"isMine":false,"isRevealed":true,"isFlagged":false}],[{"xPos":4,"yPos":0,"value":0,"isMine":false,"isRevealed":true,"isFlagged":false},{"xPos":4,"yPos":1,"value":1,"isMine":false,"isRevealed":true,"isFlagged":false},{"xPos":4,"yPos":2,"value":"M","isMine":true,"isRevealed":false,"isFlagged":true},{"xPos":4,"yPos":3,"value":1,"isMine":false,"isRevealed":true,"isFlagged":false},{"xPos":4,"yPos":4,"value":0,"isMine":false,"isRevealed":true,"isFlagged":false},{"xPos":4,"yPos":5,"value":0,"isMine":false,"isRevealed":true,"isFlagged":false},{"xPos":4,"yPos":6,"value":0,"isMine":false,"isRevealed":true,"isFlagged":false},{"xPos":4,"yPos":7,"value":0,"isMine":false,"isRevealed":true,"isFlagged":false},{"xPos":4,"yPos":8,"value":0,"isMine":false,"isRevealed":true,"isFlagged":false},{"xPos":4,"yPos":9,"value":0,"isMine":false,"isRevealed":true,"isFlagged":false}],[{"xPos":5,"yPos":0,"value":0,"isMine":false,"isRevealed":true,"isFlagged":false},{"xPos":5,"yPos":1,"value":1,"isMine":false,"isRevealed":true,"isFlagged":false},{"xPos":5,"yPos":2,"value":1,"isMine":false,"isRevealed":true,"isFlagged":false},{"xPos":5,"yPos":3,"value":1,"isMine":false,"isRevealed":true,"isFlagged":false},{"xPos":5,"yPos":4,"value":0,"isMine":false,"isRevealed":true,"isFlagged":false},{"xPos":5,"yPos":5,"value":0,"isMine":false,"isRevealed":true,"isFlagged":false},{"xPos":5,"yPos":6,"value":0,"isMine":false,"isRevealed":true,"isFlagged":false},{"xPos":5,"yPos":7,"value":0,"isMine":false,"isRevealed":true,"isFlagged":false},{"xPos":5,"yPos":8,"value":0,"isMine":false,"isRevealed":true,"isFlagged":false},{"xPos":5,"yPos":9,"value":0,"isMine":false,"isRevealed":true,"isFlagged":false}],[{"xPos":6,"yPos":0,"value":0,"isMine":false,"isRevealed":true,"isFlagged":false},{"xPos":6,"yPos":1,"value":0,"isMine":false,"isRevealed":true,"isFlagged":false},{"xPos":6,"yPos":2,"value":0,"isMine":false,"isRevealed":true,"isFlagged":false},{"xPos":6,"yPos":3,"value":0,"isMine":false,"isRevealed":true,"isFlagged":false},{"xPos":6,"yPos":4,"value":0,"isMine":false,"isRevealed":true,"isFlagged":false},{"xPos":6,"yPos":5,"value":0,"isMine":false,"isRevealed":true,"isFlagged":false},{"xPos":6,"yPos":6,"value":0,"isMine":false,"isRevealed":true,"isFlagged":false},{"xPos":6,"yPos":7,"value":0,"isMine":false,"isRevealed":true,"isFlagged":false},{"xPos":6,"yPos":8,"value":0,"isMine":false,"isRevealed":true,"isFlagged":false},{"xPos":6,"yPos":9,"value":0,"isMine":false,"isRevealed":true,"isFlagged":false}],[{"xPos":7,"yPos":0,"value":0,"isMine":false,"isRevealed":true,"isFlagged":false},{"xPos":7,"yPos":1,"value":0,"isMine":false,"isRevealed":true,"isFlagged":false},{"xPos":7,"yPos":2,"value":0,"isMine":false,"isRevealed":true,"isFlagged":false},{"xPos":7,"yPos":3,"value":0,"isMine":false,"isRevealed":true,"isFlagged":false},{"xPos":7,"yPos":4,"value":1,"isMine":false,"isRevealed":true,"isFlagged":false},{"xPos":7,"yPos":5,"value":1,"isMine":false,"isRevealed":true,"isFlagged":false},{"xPos":7,"yPos":6,"value":1,"isMine":false,"isRevealed":true,"isFlagged":false},{"xPos":7,"yPos":7,"value":0,"isMine":false,"isRevealed":true,"isFlagged":false},{"xPos":7,"yPos":8,"value":1,"isMine":false,"isRevealed":true,"isFlagged":false},{"xPos":7,"yPos":9,"value":1,"isMine":false,"isRevealed":true,"isFlagged":false}],[{"xPos":8,"yPos":0,"value":1,"isMine":false,"isRevealed":true,"isFlagged":false},{"xPos":8,"yPos":1,"value":1,"isMine":false,"isRevealed":true,"isFlagged":false},{"xPos":8,"yPos":2,"value":2,"isMine":false,"isRevealed":true,"isFlagged":false},{"xPos":8,"yPos":3,"value":1,"isMine":false,"isRevealed":true,"isFlagged":false},{"xPos":8,"yPos":4,"value":2,"isMine":false,"isRevealed":true,"isFlagged":false},{"xPos":8,"yPos":5,"value":"M","isMine":true,"isRevealed":false,"isFlagged":false},{"xPos":8,"yPos":6,"value":1,"isMine":false,"isRevealed":true,"isFlagged":false},{"xPos":8,"yPos":7,"value":0,"isMine":false,"isRevealed":true,"isFlagged":false},{"xPos":8,"yPos":8,"value":1,"isMine":false,"isRevealed":true,"isFlagged":false},{"xPos":8,"yPos":9,"value":"M","isMine":true,"isRevealed":false,"isFlagged":false}],[{"xPos":9,"yPos":0,"value":1,"isMine":false,"isRevealed":false,"isFlagged":false},{"xPos":9,"yPos":1,"value":"M","isMine":true,"isRevealed":false,"isFlagged":false},{"xPos":9,"yPos":2,"value":2,"isMine":false,"isRevealed":false,"isFlagged":false},{"xPos":9,"yPos":3,"value":"M","isMine":true,"isRevealed":false,"isFlagged":false},{"xPos":9,"yPos":4,"value":2,"isMine":false,"isRevealed":false,"isFlagged":false},{"xPos":9,"yPos":5,"value":1,"isMine":false,"isRevealed":false,"isFlagged":false},{"xPos":9,"yPos":6,"value":1,"isMine":false,"isRevealed":true,"isFlagged":false},{"xPos":9,"yPos":7,"value":0,"isMine":false,"isRevealed":true,"isFlagged":false},{"xPos":9,"yPos":8,"value":1,"isMine":false,"isRevealed":true,"isFlagged":false},{"xPos":9,"yPos":9,"value":1,"isMine":false,"isRevealed":false,"isFlagged":false}]],"minesFound":2,"falseMines":0,"playing":true,"movesMade":3,"savedGame":true,"gameOptions":{"rows":10,"cols":10,"mines":10}}